otus/__init__.py
otus/core.py
otus/main.py
otus2002web-0.1.dist-info/METADATA
otus2002web-0.1.dist-info/WHEEL
otus2002web-0.1.dist-info/entry_points.txt
otus2002web-0.1.dist-info/top_level.txt
otus2002web-0.1.dist-info/RECORD
