Metadata-Version: 2.1
Name: otus2002web
Version: 0.1
Summary: famous people text
Home-page: https://github.com/DanteOnline/django-dantejcoder
Author: Leo Orlov
Author-email: iamdanteonline@gmail.com
License: GNU General Public License v3.0
Keywords: json,django,JsonResponse,encoder
Platform: UNKNOWN
